<?xml version="1.0" encoding="UTF-8" standalone="yes"?>
<node core="-1" id="5" xmlns="http://webspace.ulbsibiu.ro/ciprian.radu/research/noc/application_mapping/unified_framework/schema/node">
    <cost>0.2840000092983246</cost>
    <topologyParameter value="0" type="row" topology="mesh2D"/>
    <topologyParameter value="5" type="column" topology="mesh2D"/>
    <link value="4" type="out"/>
    <link value="4" type="in"/>
    <link value="35" type="out"/>
    <link value="35" type="in"/>
    <routingTableEntry link="35" destination="11" source="0"/>
    <routingTableEntry link="35" destination="17" source="0"/>
    <routingTableEntry link="35" destination="23" source="0"/>
    <routingTableEntry link="35" destination="29" source="0"/>
    <routingTableEntry link="35" destination="35" source="0"/>
    <routingTableEntry link="35" destination="11" source="1"/>
    <routingTableEntry link="35" destination="17" source="1"/>
    <routingTableEntry link="35" destination="23" source="1"/>
    <routingTableEntry link="35" destination="29" source="1"/>
    <routingTableEntry link="35" destination="35" source="1"/>
    <routingTableEntry link="35" destination="11" source="2"/>
    <routingTableEntry link="35" destination="17" source="2"/>
    <routingTableEntry link="35" destination="23" source="2"/>
    <routingTableEntry link="35" destination="29" source="2"/>
    <routingTableEntry link="35" destination="35" source="2"/>
    <routingTableEntry link="35" destination="11" source="3"/>
    <routingTableEntry link="35" destination="17" source="3"/>
    <routingTableEntry link="35" destination="23" source="3"/>
    <routingTableEntry link="35" destination="29" source="3"/>
    <routingTableEntry link="35" destination="35" source="3"/>
    <routingTableEntry link="35" destination="11" source="4"/>
    <routingTableEntry link="35" destination="17" source="4"/>
    <routingTableEntry link="35" destination="23" source="4"/>
    <routingTableEntry link="35" destination="29" source="4"/>
    <routingTableEntry link="35" destination="35" source="4"/>
    <routingTableEntry link="4" destination="0" source="5"/>
    <routingTableEntry link="4" destination="1" source="5"/>
    <routingTableEntry link="4" destination="2" source="5"/>
    <routingTableEntry link="4" destination="3" source="5"/>
    <routingTableEntry link="4" destination="4" source="5"/>
    <routingTableEntry link="4" destination="6" source="5"/>
    <routingTableEntry link="4" destination="7" source="5"/>
    <routingTableEntry link="4" destination="8" source="5"/>
    <routingTableEntry link="4" destination="9" source="5"/>
    <routingTableEntry link="4" destination="10" source="5"/>
    <routingTableEntry link="35" destination="11" source="5"/>
    <routingTableEntry link="4" destination="12" source="5"/>
    <routingTableEntry link="4" destination="13" source="5"/>
    <routingTableEntry link="4" destination="14" source="5"/>
    <routingTableEntry link="4" destination="15" source="5"/>
    <routingTableEntry link="4" destination="16" source="5"/>
    <routingTableEntry link="35" destination="17" source="5"/>
    <routingTableEntry link="4" destination="18" source="5"/>
    <routingTableEntry link="4" destination="19" source="5"/>
    <routingTableEntry link="4" destination="20" source="5"/>
    <routingTableEntry link="4" destination="21" source="5"/>
    <routingTableEntry link="4" destination="22" source="5"/>
    <routingTableEntry link="35" destination="23" source="5"/>
    <routingTableEntry link="4" destination="24" source="5"/>
    <routingTableEntry link="4" destination="25" source="5"/>
    <routingTableEntry link="4" destination="26" source="5"/>
    <routingTableEntry link="4" destination="27" source="5"/>
    <routingTableEntry link="4" destination="28" source="5"/>
    <routingTableEntry link="35" destination="29" source="5"/>
    <routingTableEntry link="4" destination="30" source="5"/>
    <routingTableEntry link="4" destination="31" source="5"/>
    <routingTableEntry link="4" destination="32" source="5"/>
    <routingTableEntry link="4" destination="33" source="5"/>
    <routingTableEntry link="4" destination="34" source="5"/>
    <routingTableEntry link="35" destination="35" source="5"/>
</node>
